{
  "points": [
    {
      "t": "2026-07-21T12:54:55.345745+00:00",
      "players": 8632
    },
    {
      "t": "2026-07-21T12:57:47.372219+00:00",
      "players": 8632
    },
    {
      "t": "2026-07-21T12:59:03.626511+00:00",
      "players": 8733
    },
    {
      "t": "2026-07-21T21:53:37.923543+00:00",
      "players": 9462
    },
    {
      "t": "2026-07-21T22:16:20.503041+00:00",
      "players": 9055
    },
    {
      "t": "2026-07-21T22:34:52.139524+00:00",
      "players": 8874
    },
    {
      "t": "2026-07-22T04:33:22.805214+00:00",
      "players": 7029
    }
  ]
}
